udevbackup/__init__.py
udevbackup/__main__.py
udevbackup/cli.py
udevbackup/rule.py
udevbackup-1.4.2.dist-info/LICENSE
udevbackup-1.4.2.dist-info/METADATA
udevbackup-1.4.2.dist-info/WHEEL
udevbackup-1.4.2.dist-info/entry_points.txt
udevbackup-1.4.2.dist-info/RECORD
