Metadata-Version: 2.3
Name: udevbackup
Version: 1.4.2
Summary: detects when specified storage devices are connected, mounts them, executes a script, umounts them and tells when it is done.
License: CECILL-B
Author: Matthieu Gallet
Author-email: github@19pouces.net
Maintainer: Matthieu Gallet
Maintainer-email: github@19pouces.net
Requires-Python: >=3.11,<4.0
Classifier: Development Status :: 5 - Production/Stable
Classifier: License :: CeCILL-B Free Software License Agreement (CECILL-B)
Classifier: License :: OSI Approved :: CEA CNRS Inria Logiciel Libre License, version 2.1 (CeCILL-2.1)
Classifier: Operating System :: POSIX :: Linux
Classifier: Programming Language :: Python :: 3
Classifier: Programming Language :: Python :: 3.11
Classifier: Programming Language :: Python :: 3.12
Classifier: Programming Language :: Python :: 3.13
Classifier: Programming Language :: Python :: 3 :: Only
Classifier: Programming Language :: Python :: 3.14
Requires-Dist: fasteners (>=0.20,<0.21)
Requires-Dist: systemlogger (>=0.2.2,<0.3.0)
Requires-Dist: termcolor (>=3.2.0,<4.0.0)
Project-URL: Documentation, https://github.com/d9pouces/udevbackup
Project-URL: Repository, https://github.com/d9pouces/udevbackup
